pydebflow/__init__.py
pydebflow/core/__init__.py
pydebflow/core/flow_model.py
pydebflow/core/noc_tvd_solver.py
pydebflow/core/terrain.py
pydebflow/gui/__init__.py
pydebflow/gui/main_window.py
pydebflow/io/__init__.py
pydebflow/io/parameters.py
pydebflow/io/raster_io.py
pydebflow/io/results.py
pydebflow/physics/__init__.py
pydebflow/physics/entrainment.py
pydebflow/physics/rheology.py
pydebflow/visualization/__init__.py
pydebflow/visualization/dem_viewer.py
pydebflow/visualization/plot_utils.py
pydebflow-0.1.0.dist-info/licenses/LICENSE
pydebflow-0.1.0.dist-info/METADATA
pydebflow-0.1.0.dist-info/WHEEL
pydebflow-0.1.0.dist-info/entry_points.txt
pydebflow-0.1.0.dist-info/top_level.txt
pydebflow-0.1.0.dist-info/RECORD
