Metadata-Version: 2.4
Name: pydebflow
Version: 0.1.0
Summary: Advanced Two-Phase Mass Flow Simulation Software for debris flows, avalanches, and lahars
Author-email: Ankit Dutta <masterankit150@gmail.com>
Maintainer-email: Ankit Dutta <masterankit150@gmail.com>
License: AGPL-3.0
Project-URL: Homepage, https://github.com/ankitdutta428/PyDebFlow
Project-URL: Documentation, https://github.com/ankitdutta428/PyDebFlow#readme
Project-URL: Repository, https://github.com/ankitdutta428/PyDebFlow.git
Project-URL: Issues, https://github.com/ankitdutta428/PyDebFlow/issues
Project-URL: Changelog, https://github.com/ankitdutta428/PyDebFlow/releases
Keywords: debris-flow,avalanche,lahar,geophysics,simulation,mass-flow,hydrology,geoscience,two-phase-flow,numerical-simulation
Classifier: Development Status :: 4 - Beta
Classifier: Intended Audience :: Science/Research
Classifier: License :: OSI Approved :: GNU Affero General Public License v3
Classifier: Operating System :: OS Independent
Classifier: Programming Language :: Python :: 3
Classifier: Programming Language :: Python :: 3.10
Classifier: Programming Language :: Python :: 3.11
Classifier: Programming Language :: Python :: 3.12
Classifier: Topic :: Scientific/Engineering
Classifier: Topic :: Scientific/Engineering :: GIS
Classifier: Topic :: Scientific/Engineering :: Physics
Classifier: Topic :: Scientific/Engineering :: Visualization
Requires-Python: >=3.10
License-File: LICENSE
Requires-Dist: numpy>=1.24.0
Requires-Dist: numba>=0.57.0
Requires-Dist: scipy>=1.10.0
Requires-Dist: matplotlib>=3.7.0
Requires-Dist: pyyaml>=6.0.0
Provides-Extra: gui
Requires-Dist: PyQt6>=6.5.0; extra == "gui"
Provides-Extra: visualization
Requires-Dist: pyvista>=0.42.0; extra == "visualization"
Requires-Dist: imageio>=2.31.0; extra == "visualization"
Requires-Dist: imageio-ffmpeg>=0.4.0; extra == "visualization"
Provides-Extra: raster
Requires-Dist: rasterio>=1.3.0; extra == "raster"
Provides-Extra: dev
Requires-Dist: pytest>=7.4.0; extra == "dev"
Requires-Dist: pytest-cov>=4.0.0; extra == "dev"
Requires-Dist: black>=23.0.0; extra == "dev"
Requires-Dist: isort>=5.12.0; extra == "dev"
Requires-Dist: flake8>=6.0.0; extra == "dev"
Requires-Dist: build>=0.10.0; extra == "dev"
Requires-Dist: twine>=4.0.0; extra == "dev"
Provides-Extra: all
Requires-Dist: pydebflow[dev,gui,raster,visualization]; extra == "all"
Dynamic: license-file
